LICENSE.txt
MANIFEST.in
README.rst
mogli.py
setup.py
mogli.egg-info/PKG-INFO
mogli.egg-info/SOURCES.txt
mogli.egg-info/dependency_links.txt
mogli.egg-info/requires.txt
mogli.egg-info/top_level.txt