Metadata-Version: 1.1
Name: mogli
Version: 0.2.3
Summary: Simple visualization of molecules in python
Home-page: https://github.com/FlorianRhiem/mogli
Author: Florian Rhiem
Author-email: florian.rhiem@gmail.com
License: UNKNOWN
Platform: UNKNOWN
Classifier: Development Status :: 5 - Production/Stable
Classifier: Intended Audience :: Science/Research
Classifier: Intended Audience :: Developers
Classifier: License :: OSI Approved :: MIT License
Classifier: Programming Language :: Python
Classifier: Topic :: Scientific/Engineering :: Visualization
Classifier: Topic :: Scientific/Engineering :: Chemistry
Classifier: Topic :: Scientific/Engineering :: Physics
